wsknn/__init__.py
wsknn/fit_transform.py
wsknn/predict.py
wsknn/evaluate/__init__.py
wsknn/evaluate/metrics.py
wsknn/evaluate/simulate.py
wsknn/evaluate/scores/__init__.py
wsknn/evaluate/scores/scores.py
wsknn/import_export/__init__.py
wsknn/import_export/ie.py
wsknn/model/__init__.py
wsknn/model/validators.py
wsknn/model/wsknn.py
wsknn/preprocessing/__init__.py
wsknn/preprocessing/parse_static.py
wsknn/preprocessing/export/__init__.py
wsknn/preprocessing/export/export.py
wsknn/preprocessing/static_parsers/__init__.py
wsknn/preprocessing/static_parsers/pandas_parser.py
wsknn/preprocessing/static_parsers/parse.py
wsknn/preprocessing/static_parsers/checkers/__init__.py
wsknn/preprocessing/static_parsers/checkers/validation.py
wsknn/preprocessing/static_parsers/cleaners/__init__.py
wsknn/preprocessing/static_parsers/cleaners/time_transform.py
wsknn/preprocessing/static_parsers/csv_parser/__init__.py
wsknn/preprocessing/static_parsers/csv_parser/parse.py
wsknn/preprocessing/static_parsers/flat_file_parser/__init__.py
wsknn/preprocessing/static_parsers/flat_file_parser/parse.py
wsknn/preprocessing/static_parsers/json_parser/__init__.py
wsknn/preprocessing/static_parsers/json_parser/parse.py
wsknn/preprocessing/structure/__init__.py
wsknn/preprocessing/structure/item.py
wsknn/preprocessing/structure/session.py
wsknn/preprocessing/structure/session_to_item_map.py
wsknn/preprocessing/utils/__init__.py
wsknn/preprocessing/utils/calc.py
wsknn/preprocessing/utils/files.py
wsknn/preprocessing/utils/transform.py
wsknn/utils/__init__.py
wsknn/utils/calc.py
wsknn/utils/errors.py
wsknn/utils/meta.py
wsknn/utils/transform.py
wsknn/weighting/__init__.py
wsknn/weighting/item_weighting.py
wsknn/weighting/session_weighting.py
wsknn/weighting/weighting.py
wsknn-1.2.3.dist-info/LICENSE.md
wsknn-1.2.3.dist-info/METADATA
wsknn-1.2.3.dist-info/WHEEL
wsknn-1.2.3.dist-info/top_level.txt
wsknn-1.2.3.dist-info/RECORD
