Metadata-Version: 2.1
Name: wsknn
Version: 1.2.3
Summary: Weighted session-based model for recommendations
Home-page: https://github.com/nokaut/wsknn
Author: Szymon Moliński
Author-email: s.molinski@digitree.pl
License: MIT
Project-URL: Documentation, https://readthedocs.org/projects/wsknn/
Project-URL: Source, https://github.com/nokaut/wsknn
Project-URL: Tracker, https://github.com/nokaut/wsknn/issues
Classifier: Development Status :: 5 - Production/Stable
Classifier: Intended Audience :: Science/Research
Classifier: Intended Audience :: Information Technology
Classifier: Topic :: Internet :: WWW/HTTP :: Session
Classifier: Topic :: Scientific/Engineering :: Artificial Intelligence
Classifier: Topic :: Scientific/Engineering :: Information Analysis
Classifier: License :: OSI Approved :: MIT License
Classifier: Programming Language :: Python :: 3.8
Classifier: Programming Language :: Python :: 3.9
Classifier: Programming Language :: Python :: 3.10
Classifier: Programming Language :: Python :: 3.11
Classifier: Programming Language :: Python :: 3.12
Requires-Python: >=3.8
License-File: LICENSE.md
Requires-Dist: numpy
Requires-Dist: more-itertools
Requires-Dist: pyyaml
Requires-Dist: tqdm
Requires-Dist: pandas
